air/__init__.py
air/client.py
air/logconfig.py
air/api/__init__.py
air/api/pandas.py
air/api/postgres.py
air/api/vector_db/__init__.py
air/api/vector_db/azure_aisearch.py
air/api/vector_db/base_vectordb.py
air/api/vector_db/elastic_search.py
air/api/vector_db/vectordb_registry.py
air/audio/__init__.py
air/audio/asr_client.py
air/audio/client.py
air/audio/tts_client.py
air/auth/__init__.py
air/auth/jwt.py
air/auth/token_provider.py
air/chat/__init__.py
air/chat/client.py
air/distiller/__init__.py
air/distiller/client.py
air/distiller/exceptions.py
air/distiller/realtime_client.py
air/distiller/executor/__init__.py
air/distiller/executor/a2a_executor.py
air/distiller/executor/amazon_bedrock_executor.py
air/distiller/executor/analytics_executor.py
air/distiller/executor/azure_executor.py
air/distiller/executor/cb_insights_executor.py
air/distiller/executor/databricks_executor.py
air/distiller/executor/deep_research_executor.py
air/distiller/executor/executor.py
air/distiller/executor/google_executor.py
air/distiller/executor/human_executor.py
air/distiller/executor/mcp_executor.py
air/distiller/executor/pega_executor.py
air/distiller/executor/salesforce_executor.py
air/distiller/executor/sap_executor.py
air/distiller/executor/servicenow_executor.py
air/distiller/executor/snowflake_executor.py
air/distiller/executor/tool_executor.py
air/distiller/executor/vector_search_executor.py
air/distiller/executor/wolfram_executor.py
air/distiller/executor/writer_executor.py
air/distiller/pii_handler/__init__.py
air/distiller/pii_handler/pii_handler.py
air/distiller/pii_handler/pii_handler.yaml
air/distiller/utils/__init__.py
air/distiller/utils/realtime_helper.py
air/embeddings/__init__.py
air/embeddings/client.py
air/fine_tuning/__init__.py
air/fine_tuning/client.py
air/images/__init__.py
air/images/client.py
air/knowledge/__init__.py
air/knowledge/client.py
air/knowledge/document_processing_client.py
air/knowledge/knowledge_graph_client.py
airefinery_sdk-1.24.0.dist-info/licenses/LICENSE
airefinery_sdk-1.24.0.dist-info/METADATA
airefinery_sdk-1.24.0.dist-info/WHEEL
airefinery_sdk-1.24.0.dist-info/entry_points.txt
airefinery_sdk-1.24.0.dist-info/top_level.txt
airefinery_sdk-1.24.0.dist-info/RECORD
