Metadata-Version: 2.4
Name: airefinery-sdk
Version: 1.24.0
Summary: AI Refinery™ by Accenture SDK for developing and executing AI multi-agent solutions.
Author: Accenture
Author-email: Accenture <sdk_airefinery@accenture.com>
License: Apache-2.0
Project-URL: Homepage, https://github.com/Accenture/airefinery-sdk
Requires-Python: >=3.12
License-File: LICENSE
Requires-Dist: omegaconf>=2.2.3
Requires-Dist: requests>=2.32.2
Requires-Dist: asyncpg>=0.30.0
Requires-Dist: aiohttp[speedups]>=3.11.0
Requires-Dist: pillow>=11.0.0
Requires-Dist: websockets>=13.0
Requires-Dist: tenacity>=9.0.0
Requires-Dist: setuptools>=75.2.0
Requires-Dist: numpy>=1.26.0
Requires-Dist: pandas>=2.2.3
Requires-Dist: mcp>=1.6.0
Requires-Dist: aiofiles>=24.1.0
Requires-Dist: filelock>=3.15.3
Requires-Dist: tqdm>=4.67.0
Provides-Extra: tah-vertex-ai
Requires-Dist: google-genai==1.20.0; extra == "tah-vertex-ai"
Requires-Dist: google-cloud-aiplatform[agent_engines]==1.101.0; extra == "tah-vertex-ai"
Provides-Extra: tah-azure-ai
Requires-Dist: azure-ai-projects==1.0.0b8; extra == "tah-azure-ai"
Requires-Dist: azure-identity==1.26.0b1; extra == "tah-azure-ai"
Provides-Extra: tah-writer-ai
Requires-Dist: writer-sdk>=2.2.0; extra == "tah-writer-ai"
Provides-Extra: knowledge
Requires-Dist: graphrag==2.5.0; extra == "knowledge"
Requires-Dist: networkx>=3.4.2; extra == "knowledge"
Requires-Dist: matplotlib>=3.10.1; extra == "knowledge"
Provides-Extra: tah-aws-ai
Requires-Dist: boto3>=1.38.36; extra == "tah-aws-ai"
Provides-Extra: tah-a2a
Requires-Dist: a2a-sdk==0.2.8; extra == "tah-a2a"
Requires-Dist: langchain-core>=0.3.68; extra == "tah-a2a"
Requires-Dist: langchain-openai>=0.3.27; extra == "tah-a2a"
Requires-Dist: langgraph>=0.5.2; extra == "tah-a2a"
Provides-Extra: tah-databricks
Requires-Dist: databricks-sdk>=0.57.0; extra == "tah-databricks"
Provides-Extra: pii
Requires-Dist: presidio-analyzer>=2.2.358; extra == "pii"
Requires-Dist: presidio-anonymizer>=2.2.358; extra == "pii"
Provides-Extra: realtime
Requires-Dist: sounddevice>=0.5.1; extra == "realtime"
Provides-Extra: full
Requires-Dist: google-genai==1.20.0; extra == "full"
Requires-Dist: google-cloud-aiplatform[agent_engines]==1.101.0; extra == "full"
Requires-Dist: azure-ai-projects==1.0.0b8; extra == "full"
Requires-Dist: azure-identity==1.26.0b1; extra == "full"
Requires-Dist: writer-sdk>=2.2.0; extra == "full"
Requires-Dist: graphrag==2.5.0; extra == "full"
Requires-Dist: networkx>=3.4.2; extra == "full"
Requires-Dist: matplotlib>=3.10.1; extra == "full"
Requires-Dist: boto3>=1.38.36; extra == "full"
Requires-Dist: a2a-sdk==0.2.8; extra == "full"
Requires-Dist: langchain-core>=0.3.68; extra == "full"
Requires-Dist: langchain-openai>=0.3.27; extra == "full"
Requires-Dist: langgraph>=0.5.2; extra == "full"
Requires-Dist: databricks-sdk>=0.57.0; extra == "full"
Requires-Dist: presidio-analyzer>=2.2.358; extra == "full"
Requires-Dist: presidio-anonymizer>=2.2.358; extra == "full"
Requires-Dist: sounddevice>=0.5.1; extra == "full"
Dynamic: author
Dynamic: license-file
